pystachio/__init__.py
pystachio/base.py
pystachio/basic.py
pystachio/choice.py
pystachio/compatibility.py
pystachio/composite.py
pystachio/config.py
pystachio/container.py
pystachio/matcher.py
pystachio/naming.py
pystachio/parsing.py
pystachio/typing.py
pystachio-0.8.5.data/scripts/pystachio_repl
pystachio-0.8.5.dist-info/LICENSE
pystachio-0.8.5.dist-info/METADATA
pystachio-0.8.5.dist-info/WHEEL
pystachio-0.8.5.dist-info/top_level.txt
pystachio-0.8.5.dist-info/zip-safe
pystachio-0.8.5.dist-info/RECORD
