Metadata-Version: 2.1
Name: pystachio
Version: 0.8.5
Summary: type-checked dictionary templating library
Home-page: http://github.com/wickman/pystachio
Author: Brian Wickman
Author-email: wickman@gmail.com
License: MIT
Platform: UNKNOWN
Classifier: Programming Language :: Python
Classifier: Intended Audience :: Developers
Classifier: License :: OSI Approved :: MIT License
Classifier: Operating System :: OS Independent
